MANIFEST.in
README.rst
setup.cfg
setup.py
XStatic_Patternfly_Bootstrap_Treeview.egg-info/PKG-INFO
XStatic_Patternfly_Bootstrap_Treeview.egg-info/SOURCES.txt
XStatic_Patternfly_Bootstrap_Treeview.egg-info/dependency_links.txt
XStatic_Patternfly_Bootstrap_Treeview.egg-info/namespace_packages.txt
XStatic_Patternfly_Bootstrap_Treeview.egg-info/not-zip-safe
XStatic_Patternfly_Bootstrap_Treeview.egg-info/top_level.txt
xstatic/__init__.py
xstatic/pkg/__init__.py
xstatic/pkg/patternfly_bootstrap_treeview/__init__.py
xstatic/pkg/patternfly_bootstrap_treeview/data/css/bootstrap-treeview.css
xstatic/pkg/patternfly_bootstrap_treeview/data/css/bootstrap-treeview.min.css
xstatic/pkg/patternfly_bootstrap_treeview/data/js/bootstrap-treeview.js
xstatic/pkg/patternfly_bootstrap_treeview/data/js/bootstrap-treeview.min.js