Metadata-Version: 1.0
Name: XStatic-Patternfly-Bootstrap-Treeview
Version: 2.1.3.2
Summary: Patternfly-Bootstrap-Treeview 2.1.3 (XStatic packaging standard)
Home-page: https://www.patternfly.org/
Author: David Moreau Simard
Author-email: dmsimard@redhat.com
License: Apache v2
Keywords: patternfly_bootstrap_treeview xstatic
Platform: any
